sentiment_model/__init__.py
sentiment_model/config.yml
sentiment_model/pipeline.py
sentiment_model/predict.py
sentiment_model/train_pipeline.py
sentiment_model/config/__init__.py
sentiment_model/config/core.py
sentiment_model/datasets/twitter_training.csv
sentiment_model/processing/__init__.py
sentiment_model/processing/features.py
sentiment_model/processing/validation.py
sentiment_model/trained_models/sentiment_analysis_model_0.11.0.pkl
sentiment_analysis_package-0.11.0.dist-info/METADATA
sentiment_analysis_package-0.11.0.dist-info/WHEEL
sentiment_analysis_package-0.11.0.dist-info/top_level.txt
sentiment_analysis_package-0.11.0.dist-info/RECORD
